MANIFEST.in
README.rst
buildout.cfg
setup.py
docs/CHANGELOG.rst
docs/LICENSE.rst
src/niteoweb/__init__.py
src/niteoweb.ipn.core.egg-info/PKG-INFO
src/niteoweb.ipn.core.egg-info/SOURCES.txt
src/niteoweb.ipn.core.egg-info/dependency_links.txt
src/niteoweb.ipn.core.egg-info/entry_points.txt
src/niteoweb.ipn.core.egg-info/namespace_packages.txt
src/niteoweb.ipn.core.egg-info/not-zip-safe
src/niteoweb.ipn.core.egg-info/requires.txt
src/niteoweb.ipn.core.egg-info/top_level.txt
src/niteoweb/ipn/__init__.py
src/niteoweb/ipn/core/__init__.py
src/niteoweb/ipn/core/configure.zcml
src/niteoweb/ipn/core/interfaces.py
src/niteoweb/ipn/core/ipn.py
src/niteoweb/ipn/core/setuphandlers.py
src/niteoweb/ipn/core/testing.py
src/niteoweb/ipn/core/validity.py
src/niteoweb/ipn/core/profiles/default/memberdata_properties.xml
src/niteoweb/ipn/core/profiles/default/metadata.xml
src/niteoweb/ipn/core/profiles/default/niteoweb.ipn.core.marker.txt
src/niteoweb/ipn/core/profiles/default/propertiestool.xml
src/niteoweb/ipn/core/profiles/default/registry.xml
src/niteoweb/ipn/core/tests/__init__.py
src/niteoweb/ipn/core/tests/test_disable.py
src/niteoweb/ipn/core/tests/test_enable.py
src/niteoweb/ipn/core/tests/test_setup.py
src/niteoweb/ipn/core/tests/test_validity.py