Metadata-Version: 1.1
Name: niteoweb.ipn.core
Version: 1.5.2
Summary: Support for Instant Payment Notifications in Plone.
Home-page: http://pypi.python.org/pypi/niteoweb.ipn.core
Author: NiteoWeb Ltd.
Author-email: info@niteoweb.com
License: BSD
Keywords: Plone IPN
Platform: UNKNOWN
Classifier: Framework :: Plone
Classifier: Programming Language :: Python
